config/__init__.py
config/config.py
gemini_agents_toolbox/__init__.py
gemini_agents_toolbox/agent.py
gemini_agents_toolbox/bin/__init__.py
gemini_agents_toolbox/bin/pipe.py
gemini_agents_toolbox/scheduler/__init__.py
gemini_agents_toolbox/scheduler/task.py
gemini_agents_toolkit/__init__.py
gemini_agents_toolkit/agent.py
gemini_agents_toolkit/agent_utils.py
gemini_agents_toolkit/history_utils.py
gemini_agents_toolkit/bin/__init__.py
gemini_agents_toolkit/bin/pipe.py
gemini_agents_toolkit/pipeline/__init__.py
gemini_agents_toolkit/pipeline/abstract_step.py
gemini_agents_toolkit/pipeline/basic_step.py
gemini_agents_toolkit/pipeline/eager_pipeline.py
gemini_agents_toolkit/pipeline/if_step.py
gemini_agents_toolkit/pipeline/pipeline_agent.py
gemini_agents_toolkit/pipeline/summary_step.py
gemini_agents_toolkit/pipeline/terminal_step.py
gemini_agents_toolkit/scheduler/__init__.py
gemini_agents_toolkit/scheduler/task.py
gemini_toolbox/__init__.py
gemini_toolbox/client.py
gemini_toolbox/declarations.py
gemini_toolbox/bin/__init__.py
gemini_toolbox/bin/pipe.py
gemini_toolbox/scheduler/__init__.py
gemini_toolbox/scheduler/task.py
gemini_agents_toolkit-3.8.3.dist-info/LICENSE
gemini_agents_toolkit-3.8.3.dist-info/METADATA
gemini_agents_toolkit-3.8.3.dist-info/WHEEL
gemini_agents_toolkit-3.8.3.dist-info/top_level.txt
gemini_agents_toolkit-3.8.3.dist-info/RECORD
