Metadata-Version: 2.1
Name: gemini_agents_toolkit
Version: 3.8.3
Summary: Toolkit For Creating Gemini Based Agents
Author: Viacheslav Kovalevskyi
Author-email: viacheslav@kovalevskyi.com
License: MIT
License-File: LICENSE
Requires-Dist: APScheduler==3.10.4
Requires-Dist: google-cloud-storage==2.18.2
Requires-Dist: google-cloud-aiplatform==1.68.*
Requires-Dist: tenacity==9.0.*
